setup.py
beswitch/__init__.py
beswitch/beswitch.py
beswitch/client.py
beswitch.egg-info/PKG-INFO
beswitch.egg-info/SOURCES.txt
beswitch.egg-info/dependency_links.txt
beswitch.egg-info/not-zip-safe
beswitch.egg-info/top_level.txt