Metadata-Version: 1.1
Name: beswitch
Version: 0.1
Summary: Backend switch for Python packages
Home-page: https://bitbucket.org/thoughteer/beswitch
Author: Iskander Sitdikov
Author-email: thoughteer@gmail.com
License: MIT
Keywords: backend frontend facade adaptor
Platform: UNKNOWN
Classifier: Development Status :: 4 - Beta
Classifier: License :: OSI Approved :: MIT License
Classifier: Programming Language :: Python :: 3.4
Classifier: Topic :: Software Development :: Libraries :: Python Modules
